external_systems/__init__.py
external_systems/_version.py
external_systems/py.typed
external_systems/sources/__init__.py
external_systems/sources/_api.py
external_systems/sources/_connections.py
external_systems/sources/_proxies.py
external_systems/sources/_refreshable.py
external_systems/sources/_sockets.py
external_systems/sources/_sources.py
external_systems/sources/_utils.py
external_systems-0.110.0.dist-info/METADATA
external_systems-0.110.0.dist-info/WHEEL
external_systems-0.110.0.dist-info/licenses/LICENSE.txt
external_systems-0.110.0.dist-info/RECORD
