Metadata-Version: 2.4
Name: external-systems
Version: 0.110.0
Summary: A Python library for interacting with Foundry Sources
License-Expression: Apache-2.0
License-File: LICENSE.txt
Keywords: Palantir,Foundry,Sources,Compute Modules,Python Functions,Transforms
Author: Palantir Technologies Inc.
Requires-Python: >=3.10,<4.0
Classifier: Programming Language :: Python :: 3
Classifier: Programming Language :: Python :: 3.10
Classifier: Programming Language :: Python :: 3.11
Classifier: Programming Language :: Python :: 3.12
Classifier: Programming Language :: Python :: 3.13
Classifier: Programming Language :: Python :: 3.14
Requires-Dist: frozendict (>=2.4.6,<3.0.0)
Requires-Dist: requests (>=2.32.3,<3.0.0)
